[
  {
    "code": 4,
    "en-gb": "Afghan",
    "cy": "Afghan"
  },
  {
    "code": 8,
    "en-gb": "Albanian",
    "cy": "Albaneg"
  },
  {
    "code": 12,
    "en-gb": "Algerian",
    "cy": "Algeria"
  },
  {
    "code": 987,
    "en-gb": "Andean",
    "cy": "Andes"
  },
  {
    "code": 20,
    "en-gb": "Andorran",
    "cy": "Andorran"
  },
  {
    "code": 24,
    "en-gb": "Angolan",
    "cy": "Angolan"
  },
  {
    "code": 28,
    "en-gb": "Antiguan and barbudan",
    "cy": "Antiguan a barbudan"
  },
  {
    "code": 32,
    "en-gb": "Argentine",
    "cy": "Ariannin"
  },
  {
    "code": 51,
    "en-gb": "Armenian",
    "cy": "Armenia"
  },
  {
    "code": 36,
    "en-gb": "Australian",
    "cy": "Awstralia"
  },
  {
    "code": 40,
    "en-gb": "Austrian",
    "cy": "Awstria"
  },
  {
    "code": 31,
    "en-gb": "Azerbaijani",
    "cy": "azerbaijani"
  },
  {
    "code": 44,
    "en-gb": "Bahamian",
    "cy": "Bahamas"
  },
  {
    "code": 48,
    "en-gb": "Bahraini",
    "cy": "Bahraini"
  },
  {
    "code": 50,
    "en-gb": "Bangladeshi",
    "cy": "Bangladeshaidd"
  },
  {
    "code": 52,
    "en-gb": "Barbados",
    "cy": "Barbados"
  },
  {
    "code": 112,
    "en-gb": "Belarusian",
    "cy": "Belarwseg"
  },
  {
    "code": 56,
    "en-gb": "Belgian",
    "cy": "Gwlad Belg"
  },
  {
    "code": 84,
    "en-gb": "Belizean",
    "cy": "Belizean"
  },
  {
    "code": 204,
    "en-gb": "Beninese",
    "cy": "Beninese"
  },
  {
    "code": 64,
    "en-gb": "Bhutanese",
    "cy": "Bhutan"
  },
  {
    "code": 68,
    "en-gb": "Bolivian",
    "cy": "Bolifia"
  },
  {
    "code": 70,
    "en-gb": "Bosnian and herzegovinian",
    "cy": "Bosnian a herzegovinian"
  },
  {
    "code": 72,
    "en-gb": "Botswana",
    "cy": "Botswana"
  },
  {
    "code": 76,
    "en-gb": "Brazilian",
    "cy": "Brasil"
  },
  {
    "code": 929,
    "en-gb": "British overseas territories (bot)",
    "cy": "diriogaethau tramor Prydain (bot)"
  },
  {
    "code": 96,
    "en-gb": "Bruneian",
    "cy": "Bruneian"
  },
  {
    "code": 100,
    "en-gb": "Bulgarian",
    "cy": "Bwlgareg"
  },
  {
    "code": 854,
    "en-gb": "Burkinabe",
    "cy": "Burkinabe"
  },
  {
    "code": 104,
    "en-gb": "Burmese",
    "cy": "Burmese"
  },
  {
    "code": 108,
    "en-gb": "Burundian",
    "cy": "Burundi"
  },
  {
    "code": 116,
    "en-gb": "Cambodian",
    "cy": "Cambodieg"
  },
  {
    "code": 120,
    "en-gb": "Cameroonian",
    "cy": "Cameroon"
  },
  {
    "code": 124,
    "en-gb": "Canadian",
    "cy": "Canada"
  },
  {
    "code": 132,
    "en-gb": "Cape verdean",
    "cy": "Cape Verde"
  },
  {
    "code": 148,
    "en-gb": "Chadian",
    "cy": "Chadian"
  },
  {
    "code": 152,
    "en-gb": "Chilean",
    "cy": "Chile"
  },
  {
    "code": 156,
    "en-gb": "Chinese",
    "cy": "Tseiniaidd"
  },
  {
    "code": 170,
    "en-gb": "Colombian",
    "cy": "Colombia"
  },
  {
    "code": 174,
    "en-gb": "Comorian",
    "cy": "Comorian"
  },
  {
    "code": 188,
    "en-gb": "Costa rican",
    "cy": "Costa Rica"
  },
  {
    "code": 191,
    "en-gb": "Croatian",
    "cy": "Croateg"
  },
  {
    "code": 192,
    "en-gb": "Cuban",
    "cy": "Ciwba"
  },
  {
    "code": 901,
    "en-gb": "Cypriot",
    "cy": "Chypriad"
  },
  {
    "code": 203,
    "en-gb": "Czech",
    "cy": "Tsiec"
  },
  {
    "code": 208,
    "en-gb": "Danish",
    "cy": "Daneg"
  },
  {
    "code": 408,
    "en-gb": "Democratic peoples republic of korea",
    "cy": "gweriniaeth pobl Ddemocrataidd Korea"
  },
  {
    "code": 180,
    "en-gb": "Democratic republic of the congo",
    "cy": "gweriniaeth ddemocrataidd o'r Congo"
  },
  {
    "code": 262,
    "en-gb": "Djiboutian",
    "cy": "Djiboutian"
  },
  {
    "code": 212,
    "en-gb": "Dominica",
    "cy": "Dominica"
  },
  {
    "code": 214,
    "en-gb": "Dominican republic",
    "cy": "Dominica gweriniaeth"
  },
  {
    "code": 528,
    "en-gb": "Dutch",
    "cy": "Iseldireg"
  },
  {
    "code": 626,
    "en-gb": "East timorese",
    "cy": "Dwyrain timorese"
  },
  {
    "code": 218,
    "en-gb": "Ecuadorian",
    "cy": "Ecwador"
  },
  {
    "code": 818,
    "en-gb": "Egyptian",
    "cy": "Aifft"
  },
  {
    "code": 784,
    "en-gb": "Emirati",
    "cy": "Emirati"
  },
  {
    "code": 226,
    "en-gb": "Equatorial guinean",
    "cy": "Gyhydeddol Guinea"
  },
  {
    "code": 232,
    "en-gb": "Eritrean",
    "cy": "Eritreaidd"
  },
  {
    "code": 233,
    "en-gb": "Estonian",
    "cy": "Estoneg"
  },
  {
    "code": 231,
    "en-gb": "Ethiopian",
    "cy": "Ethiopia"
  },
  {
    "code": 981,
    "en-gb": "European union",
    "cy": "Yr Undeb Ewropeaidd"
  },
  {
    "code": 242,
    "en-gb": "Fijian",
    "cy": "Fijian"
  },
  {
    "code": 246,
    "en-gb": "Finnish",
    "cy": "Ffindir"
  },
  {
    "code": 250,
    "en-gb": "French",
    "cy": "Ffrangeg"
  },
  {
    "code": 266,
    "en-gb": "Gabonese",
    "cy": "Gabon"
  },
  {
    "code": 270,
    "en-gb": "Gambian",
    "cy": "Gambia"
  },
  {
    "code": 268,
    "en-gb": "Georgian",
    "cy": "georgian"
  },
  {
    "code": 276,
    "en-gb": "German",
    "cy": "Almaeneg"
  },
  {
    "code": 288,
    "en-gb": "Ghanaian",
    "cy": "Ghana"
  },
  {
    "code": 300,
    "en-gb": "Greek",
    "cy": "Groeg"
  },
  {
    "code": 901,
    "en-gb": "Greek cypriot",
    "cy": "Chypriad Groeg"
  },
  {
    "code": 308,
    "en-gb": "Grenadian",
    "cy": "Grenadian"
  },
  {
    "code": 320,
    "en-gb": "Guatemalan",
    "cy": "Guatemalan"
  },
  {
    "code": 624,
    "en-gb": "Guinea-bissaun",
    "cy": "Guinea-bissaun"
  },
  {
    "code": 324,
    "en-gb": "Guinean",
    "cy": "Guinean"
  },
  {
    "code": 328,
    "en-gb": "Guyanese",
    "cy": "Gaiana"
  },
  {
    "code": 332,
    "en-gb": "Haitian",
    "cy": "haitian"
  },
  {
    "code": 340,
    "en-gb": "Honduran",
    "cy": "Honduras"
  },
  {
    "code": 344,
    "en-gb": "Hong kong",
    "cy": "hong kong"
  },
  {
    "code": 348,
    "en-gb": "Hungarian",
    "cy": "Hwngareg"
  },
  {
    "code": 352,
    "en-gb": "Icelandic",
    "cy": "Islandeg"
  },
  {
    "code": 356,
    "en-gb": "Indian",
    "cy": "Indiaidd"
  },
  {
    "code": 360,
    "en-gb": "Indonesian",
    "cy": "indonesian"
  },
  {
    "code": 364,
    "en-gb": "Iranian",
    "cy": "Iran"
  },
  {
    "code": 368,
    "en-gb": "Iraqi",
    "cy": "Irac"
  },
  {
    "code": 376,
    "en-gb": "Israeli",
    "cy": "Israel"
  },
  {
    "code": 380,
    "en-gb": "Italian",
    "cy": "Eidaleg"
  },
  {
    "code": 384,
    "en-gb": "Ivorian",
    "cy": "Ivorian"
  },
  {
    "code": 388,
    "en-gb": "Jamaican",
    "cy": "Jamaican"
  },
  {
    "code": 392,
    "en-gb": "Japanese",
    "cy": "Siapan"
  },
  {
    "code": 400,
    "en-gb": "Jordanian",
    "cy": "Jordanian"
  },
  {
    "code": 398,
    "en-gb": "Kazakhstani",
    "cy": "Kazakhstani"
  },
  {
    "code": 404,
    "en-gb": "Kenyan",
    "cy": "Kenya"
  },
  {
    "code": 296,
    "en-gb": "Kiribati",
    "cy": "Kiribati"
  },
  {
    "code": 951,
    "en-gb": "Kosovan",
    "cy": "Kosovo"
  },
  {
    "code": 414,
    "en-gb": "Kuwaiti",
    "cy": "Kuwaiti"
  },
  {
    "code": 417,
    "en-gb": "Kyrgyzstani",
    "cy": "Kyrgyzstani"
  },
  {
    "code": 418,
    "en-gb": "Laotian",
    "cy": "Laotian"
  },
  {
    "code": 428,
    "en-gb": "Latvian",
    "cy": "Latfieg"
  },
  {
    "code": 422,
    "en-gb": "Lebanese",
    "cy": "Libanus"
  },
  {
    "code": 426,
    "en-gb": "Lesotho",
    "cy": "Lesotho"
  },
  {
    "code": 430,
    "en-gb": "Liberian",
    "cy": "Liberian"
  },
  {
    "code": 434,
    "en-gb": "Libyan",
    "cy": "Libya"
  },
  {
    "code": 438,
    "en-gb": "Liechtenstein",
    "cy": "Liechtenstein"
  },
  {
    "code": 440,
    "en-gb": "Lithuanian",
    "cy": "Lithwaneg"
  },
  {
    "code": 442,
    "en-gb": "Luxembourg",
    "cy": "Lwcsembwrg"
  },
  {
    "code": 446,
    "en-gb": "Macao",
    "cy": "Macao"
  },
  {
    "code": 807,
    "en-gb": "Macedonian",
    "cy": "macedonian"
  },
  {
    "code": 450,
    "en-gb": "Madagascar",
    "cy": "Madagascar"
  },
  {
    "code": 454,
    "en-gb": "Malawian",
    "cy": "Malawi"
  },
  {
    "code": 458,
    "en-gb": "Malaysian",
    "cy": "Malaysia"
  },
  {
    "code": 462,
    "en-gb": "Maldivan",
    "cy": "Maldivan"
  },
  {
    "code": 466,
    "en-gb": "Malian",
    "cy": "Mali"
  },
  {
    "code": 470,
    "en-gb": "Maltese",
    "cy": "maltese"
  },
  {
    "code": 584,
    "en-gb": "Marshallese",
    "cy": "Marshallese"
  },
  {
    "code": 478,
    "en-gb": "Mauritanian",
    "cy": "Mauritania"
  },
  {
    "code": 480,
    "en-gb": "Mauritian",
    "cy": "Mauritian"
  },
  {
    "code": 484,
    "en-gb": "Mexican",
    "cy": "Mecsicanaidd"
  },
  {
    "code": 583,
    "en-gb": "Micronesian",
    "cy": "Micronesian"
  },
  {
    "code": 498,
    "en-gb": "Moldova",
    "cy": "Moldofa"
  },
  {
    "code": 492,
    "en-gb": "Monaco",
    "cy": "Monaco"
  },
  {
    "code": 496,
    "en-gb": "Mongolian",
    "cy": "Mongolian"
  },
  {
    "code": 499,
    "en-gb": "Montenegro",
    "cy": "montenegro"
  },
  {
    "code": 504,
    "en-gb": "Moroccan",
    "cy": "Moroco"
  },
  {
    "code": 508,
    "en-gb": "Mozambican",
    "cy": "Mozambican"
  },
  {
    "code": 104,
    "en-gb": "Myanmar",
    "cy": "Myanmar"
  },
  {
    "code": 516,
    "en-gb": "Namibian",
    "cy": "Namibian"
  },
  {
    "code": 520,
    "en-gb": "Nauruan",
    "cy": "Nauruan"
  },
  {
    "code": 524,
    "en-gb": "Nepalese",
    "cy": "Nepal"
  },
  {
    "code": 999,
    "en-gb": "Netherlands antilles",
    "cy": "Antilles yr Iseldiroedd"
  },
  {
    "code": 554,
    "en-gb": "New zealand",
    "cy": "Seland Newydd"
  },
  {
    "code": 558,
    "en-gb": "Nicaraguan",
    "cy": "Nicaragwa"
  },
  {
    "code": 566,
    "en-gb": "Nigerian (nigeria)",
    "cy": "Nigeria (nigeria)"
  },
  {
    "code": 562,
    "en-gb": "Nigerien (niger)",
    "cy": "Nigerien (niger)"
  },
  {
    "code": 408,
    "en-gb": "North korean",
    "cy": "Gogledd korean"
  },
  {
    "code": 902,
    "en-gb": "Northern cypriot",
    "cy": "Northern Chypriad"
  },
  {
    "code": 578,
    "en-gb": "Norwegian",
    "cy": "norwegian"
  },
  {
    "code": 512,
    "en-gb": "Omani",
    "cy": "Oman"
  },
  {
    "code": 586,
    "en-gb": "Pakistani",
    "cy": "Pacistanaidd"
  },
  {
    "code": 585,
    "en-gb": "Palauan",
    "cy": "Palauan"
  },
  {
    "code": 275,
    "en-gb": "Palestinian",
    "cy": "Palesteina"
  },
  {
    "code": 591,
    "en-gb": "Panamanian",
    "cy": "Panamanian"
  },
  {
    "code": 598,
    "en-gb": "Papua new guinean",
    "cy": "Papua Guinea newydd"
  },
  {
    "code": 600,
    "en-gb": "Paraguayan",
    "cy": "Paraguayan"
  },
  {
    "code": 604,
    "en-gb": "Peruvian",
    "cy": "Periw"
  },
  {
    "code": 608,
    "en-gb": "Philippine",
    "cy": "Philippine"
  },
  {
    "code": 616,
    "en-gb": "Polish",
    "cy": "Pwyleg"
  },
  {
    "code": 620,
    "en-gb": "Portuguese",
    "cy": "Portiwgaleg"
  },
  {
    "code": 634,
    "en-gb": "Qatari",
    "cy": "Qatar"
  },
  {
    "code": 410,
    "en-gb": "Republic of korea",
    "cy": "Gweriniaeth o Korea"
  },
  {
    "code": 178,
    "en-gb": "Republic of the congo",
    "cy": "Gweriniaeth y Congo"
  },
  {
    "code": 642,
    "en-gb": "Romanian",
    "cy": "Rwmaneg"
  },
  {
    "code": 643,
    "en-gb": "Russian",
    "cy": "Rwsieg"
  },
  {
    "code": 646,
    "en-gb": "Rwandan",
    "cy": "Rwanda"
  },
  {
    "code": 222,
    "en-gb": "Salvadoran",
    "cy": "Salvadoran"
  },
  {
    "code": 882,
    "en-gb": "Samoan",
    "cy": "Samoa"
  },
  {
    "code": 674,
    "en-gb": "San marino",
    "cy": "san Marino"
  },
  {
    "code": 678,
    "en-gb": "Santomean",
    "cy": "Santomean"
  },
  {
    "code": 682,
    "en-gb": "Saudi arabian",
    "cy": "Saudi Arabia"
  },
  {
    "code": 686,
    "en-gb": "Senegalese",
    "cy": "Senegal"
  },
  {
    "code": 688,
    "en-gb": "Serbian",
    "cy": "Serbia"
  },
  {
    "code": 690,
    "en-gb": "Seychellois",
    "cy": "Seychellois"
  },
  {
    "code": 694,
    "en-gb": "Sierra leonean",
    "cy": "Sierra Leone"
  },
  {
    "code": 702,
    "en-gb": "Singapore",
    "cy": "Singapore"
  },
  {
    "code": 703,
    "en-gb": "Slovak",
    "cy": "Slofaceg"
  },
  {
    "code": 705,
    "en-gb": "Slovenian",
    "cy": "slovenian"
  },
  {
    "code": 90,
    "en-gb": "Solomon islands",
    "cy": "ynysoedd solomon"
  },
  {
    "code": 706,
    "en-gb": "Somali",
    "cy": "Somali"
  },
  {
    "code": 710,
    "en-gb": "South african",
    "cy": "De african"
  },
  {
    "code": 410,
    "en-gb": "South korean",
    "cy": "De korean"
  },
  {
    "code": 728,
    "en-gb": "South sudanese",
    "cy": "De Sudan"
  },
  {
    "code": 901,
    "en-gb": "Southern cypriot",
    "cy": "Southern Chypriad"
  },
  {
    "code": 913,
    "en-gb": "Spanish",
    "cy": "Sbaeneg"
  },
  {
    "code": 144,
    "en-gb": "Sri lankan",
    "cy": "Sri Lanka"
  },
  {
    "code": 659,
    "en-gb": "St kitts and nevis",
    "cy": "Kitts St a Nevis"
  },
  {
    "code": 662,
    "en-gb": "St lucian",
    "cy": "St Lucian"
  },
  {
    "code": 670,
    "en-gb": "St vincent and the grenadines",
    "cy": "St Vincent a'r Grenadines"
  },
  {
    "code": 729,
    "en-gb": "Sudanese",
    "cy": "Swdan"
  },
  {
    "code": 740,
    "en-gb": "Surinamese",
    "cy": "Surinamese"
  },
  {
    "code": 748,
    "en-gb": "Swazi",
    "cy": "Swazi"
  },
  {
    "code": 752,
    "en-gb": "Swedish",
    "cy": "Swedeg"
  },
  {
    "code": 756,
    "en-gb": "Swiss",
    "cy": "Swistir"
  },
  {
    "code": 760,
    "en-gb": "Syrian",
    "cy": "Syria"
  },
  {
    "code": 158,
    "en-gb": "Taiwan",
    "cy": "Taiwan"
  },
  {
    "code": 762,
    "en-gb": "Tajikistan",
    "cy": "Tajikistan"
  },
  {
    "code": 834,
    "en-gb": "Tanzanian",
    "cy": "Tanzanian"
  },
  {
    "code": 764,
    "en-gb": "Thai",
    "cy": "thai"
  },
  {
    "code": 768,
    "en-gb": "Togolese",
    "cy": "Togo"
  },
  {
    "code": 776,
    "en-gb": "Tongan",
    "cy": "Tongan"
  },
  {
    "code": 780,
    "en-gb": "Trinidad and tobago",
    "cy": "Trinidad a Tobago"
  },
  {
    "code": 788,
    "en-gb": "Tunisian",
    "cy": "Tunisian"
  },
  {
    "code": 792,
    "en-gb": "Turkish",
    "cy": "turkish"
  },
  {
    "code": 902,
    "en-gb": "Turkish cypriot",
    "cy": "Chypriad Twrcaidd"
  },
  {
    "code": 795,
    "en-gb": "Turkmenistan",
    "cy": "Turkmenistan"
  },
  {
    "code": 798,
    "en-gb": "Tuvaluan",
    "cy": "Tuvaluan"
  },
  {
    "code": 800,
    "en-gb": "Ugandan",
    "cy": "Uganda"
  },
  {
    "code": 804,
    "en-gb": "Ukrainian",
    "cy": "Wcreineg"
  },
  {
    "code": 840,
    "en-gb": "United states",
    "cy": "Unol Daleithiau"
  },
  {
    "code": 858,
    "en-gb": "Uruguayan",
    "cy": "Uruguayan"
  },
  {
    "code": 860,
    "en-gb": "Uzbekistan",
    "cy": "Uzbekistan"
  },
  {
    "code": 548,
    "en-gb": "Vanuatu",
    "cy": "Vanuatu"
  },
  {
    "code": 336,
    "en-gb": "Vatican",
    "cy": "Fatican"
  },
  {
    "code": 862,
    "en-gb": "Venezuelan",
    "cy": "Venezuela"
  },
  {
    "code": 704,
    "en-gb": "Vietnamese",
    "cy": "Fietnameg"
  },
  {
    "code": 887,
    "en-gb": "Yemeni",
    "cy": "Yemeni"
  },
  {
    "code": 894,
    "en-gb": "Zambian",
    "cy": "Zambia"
  },
  {
    "code": 716,
    "en-gb": "Zimbabwean",
    "cy": "Zimbabwe"
  }
]
